motioncorr/__init__.py
motioncorr/bibtex.py
motioncorr/constants.py
motioncorr/convert.py
motioncorr/protocols.conf
motioncorr/viewers.py
motioncorr/protocols/__init__.py
motioncorr/protocols/protocol_base.py
motioncorr/protocols/protocol_motioncorr.py
motioncorr/protocols/protocol_motioncorr_tasks.py
motioncorr/protocols/protocol_ts_motioncor.py
motioncorr/tests/__init__.py
motioncorr/tests/test_protocols_motioncor.py
motioncorr/tests/test_protocols_tomo.py
scipion_em_motioncorr-3.16.7.dist-info/LICENSE
scipion_em_motioncorr-3.16.7.dist-info/METADATA
scipion_em_motioncorr-3.16.7.dist-info/WHEEL
scipion_em_motioncorr-3.16.7.dist-info/entry_points.txt
scipion_em_motioncorr-3.16.7.dist-info/top_level.txt
scipion_em_motioncorr-3.16.7.dist-info/RECORD
