Metadata-Version: 2.1
Name: scipion-em-motioncorr
Version: 3.16.7
Summary: Plugin to use motioncor programs within the Scipion framework
Home-page: https://github.com/scipion-em/scipion-em-motioncorr
Author: Grigory Sharov, J.M. De la Rosa Trevin
Author-email: sharov.grigory@gmail.com, delarosatrevin@scilifelab.se
License: UNKNOWN
Project-URL: Bug Reports, https://github.com/scipion-em/scipion-em-motioncorr/issues
Project-URL: Source, https://github.com/scipion-em/scipion-em-motioncorr/
Keywords: scipion electron-microscopy cryo-em structural-biology image-processing scipion-3.0
Platform: UNKNOWN
Classifier: Development Status :: 5 - Production/Stable
Classifier: License :: OSI Approved :: GNU General Public License v3 (GPLv3)
Classifier: Programming Language :: Python :: 3
Requires-Dist: scipion-em
Requires-Dist: emtable>=0.0.14
Requires-Dist: emtools==0.1.0
Requires-Dist: scipion-em-relion
Requires-Dist: tifffile
